DilixinxixitongJichuYuanli/README.md
DilixinxixitongJichuYuanli/__init__.py
DilixinxixitongJichuYuanli/__main__.py
DilixinxixitongJichuYuanli/file.epub
DilixinxixitongJichuYuanli/index.html
DilixinxixitongJichuYuanli/css/__init__.py
DilixinxixitongJichuYuanli/css/annotations.css
DilixinxixitongJichuYuanli/css/main.css
DilixinxixitongJichuYuanli/css/normalize.css
DilixinxixitongJichuYuanli/css/popup.css
DilixinxixitongJichuYuanli/font/__init__.py
DilixinxixitongJichuYuanli/font/fontello.eot
DilixinxixitongJichuYuanli/font/fontello.svg
DilixinxixitongJichuYuanli/font/fontello.ttf
DilixinxixitongJichuYuanli/font/fontello.woff
DilixinxixitongJichuYuanli/img/__init__.py
DilixinxixitongJichuYuanli/img/annotator-glyph-sprite.png
DilixinxixitongJichuYuanli/img/annotator-icon-sprite.png
DilixinxixitongJichuYuanli/img/apple-touch-icon.png
DilixinxixitongJichuYuanli/img/cancelfullscreen.png
DilixinxixitongJichuYuanli/img/close.png
DilixinxixitongJichuYuanli/img/fullscreen.png
DilixinxixitongJichuYuanli/img/loader.gif
DilixinxixitongJichuYuanli/img/menu-icon.png
DilixinxixitongJichuYuanli/img/save.png
DilixinxixitongJichuYuanli/img/saved.png
DilixinxixitongJichuYuanli/img/settings-s.png
DilixinxixitongJichuYuanli/img/settings.png
DilixinxixitongJichuYuanli/img/star.png
DilixinxixitongJichuYuanli/js/__init__.py
DilixinxixitongJichuYuanli/js/epub.js
DilixinxixitongJichuYuanli/js/epub.min.js
DilixinxixitongJichuYuanli/js/epub.min.map
DilixinxixitongJichuYuanli/js/hooks.min.js
DilixinxixitongJichuYuanli/js/hooks.min.map
DilixinxixitongJichuYuanli/js/reader.js
DilixinxixitongJichuYuanli/js/reader.js.map
DilixinxixitongJichuYuanli/js/reader.min.js
DilixinxixitongJichuYuanli/js/reader.min.map
DilixinxixitongJichuYuanli/js/hooks/__init__.py
DilixinxixitongJichuYuanli/js/hooks/extensions/__init__.py
DilixinxixitongJichuYuanli/js/hooks/extensions/highlight.js
DilixinxixitongJichuYuanli/js/libs/__init__.py
DilixinxixitongJichuYuanli/js/libs/jquery.min.js
dilixinxixitong_jichu_yuanli-2024.3.4.0.dist-info/METADATA
dilixinxixitong_jichu_yuanli-2024.3.4.0.dist-info/WHEEL
dilixinxixitong_jichu_yuanli-2024.3.4.0.dist-info/entry_points.txt
dilixinxixitong_jichu_yuanli-2024.3.4.0.dist-info/top_level.txt
dilixinxixitong_jichu_yuanli-2024.3.4.0.dist-info/RECORD
